tkitScrapyMiddleware/__init__.py
tkitScrapyMiddleware/proxy.py
tkitScrapyMiddleware-0.0.1.dist-info/LICENSE
tkitScrapyMiddleware-0.0.1.dist-info/METADATA
tkitScrapyMiddleware-0.0.1.dist-info/WHEEL
tkitScrapyMiddleware-0.0.1.dist-info/top_level.txt
tkitScrapyMiddleware-0.0.1.dist-info/RECORD
