Metadata-Version: 2.1
Name: tkitScrapyMiddleware
Version: 0.0.1
Summary: Terry toolkit sdk for tkitScrapyMiddleware ,
Home-page: https://github.com/napoler/tkitScrapyMiddleware
Author: Terry Chan
Author-email: napoler2008@gmail.com
License: UNKNOWN
Platform: UNKNOWN
License-File: LICENSE
